example_tests/__init__.py
example_tests/test_mod1.py
example_tests/test_mod2.py
pytest_fast_first/__init__.py
pytest_fast_first-1.0.5.dist-info/METADATA
pytest_fast_first-1.0.5.dist-info/WHEEL
pytest_fast_first-1.0.5.dist-info/entry_points.txt
pytest_fast_first-1.0.5.dist-info/top_level.txt
pytest_fast_first-1.0.5.dist-info/RECORD
