Metadata-Version: 2.1
Name: pytest-fast-first
Version: 1.0.5
Summary: Pytest plugin that runs fast tests first
Home-page: https://github.com/moser/pytest-fast-first
Author: Martin Vielsmaier
Author-email: moser@moserei.de
Classifier: Development Status :: 3 - Alpha
Classifier: License :: OSI Approved :: MIT License
Classifier: Framework :: Pytest
Classifier: Intended Audience :: Developers
Classifier: Topic :: Software Development :: Testing
Classifier: Programming Language :: Python
Classifier: Programming Language :: Python :: 3
Classifier: Programming Language :: Python :: 3.6
Classifier: Programming Language :: Python :: 3.7
Classifier: Programming Language :: Python :: 3.8
Classifier: Programming Language :: Python :: 3.9
Requires-Dist: pytest
